scitree/__init__.py
scitree/__main__.py
scitree/_version.py
scitree/styling.py
scitree/tree.py
scitree-0.5.3.dist-info/LICENSE
scitree-0.5.3.dist-info/METADATA
scitree-0.5.3.dist-info/WHEEL
scitree-0.5.3.dist-info/entry_points.txt
scitree-0.5.3.dist-info/top_level.txt
scitree-0.5.3.dist-info/RECORD
